CHANGES.rst
LICENSE.txt
README.rst
TODO.txt
screenshot.png
setup.py
eye/__init__.py
eye/models.py
eye/patch.py
eye/views.py
eye.egg-info/PKG-INFO
eye.egg-info/SOURCES.txt
eye.egg-info/dependency_links.txt
eye.egg-info/entry_points.txt
eye.egg-info/not-zip-safe
eye.egg-info/requires.txt
eye.egg-info/top_level.txt
eye/static/eye.css
eye/static/eye.js
eye/static/icons.gif
eye/static/index.html
eye/static/jquery.dynatree.js
eye/static/jquery.js
eye/static/jquery.layout.js
eye/static/jquery.ui.js
eye/static/loading.gif
eye/static/ui.dynatree.css
eye/static/vline.gif