Metadata-Version: 1.0
Name: eye
Version: 1.0
Summary: A generic web-based browser of ZODB databases.
Home-page: http://github.com/davisagli/eye
Author: David Glick
Author-email: dglick@gmail.com
License: UNKNOWN
Keywords: zodb pyramid zope inspector
Platform: UNKNOWN
Classifier: Development Status :: 3 - Alpha
Classifier: Environment :: Web Environment
Classifier: Intended Audience :: Developers
Classifier: License :: OSI Approved :: MIT License
Classifier: Programming Language :: Python
Classifier: Programming Language :: Python :: 2.6
Classifier: Framework :: Paste
Classifier: Framework :: ZODB
Classifier: Topic :: Internet :: WWW/HTTP :: WSGI :: Application
